nonebot_plugin_firexN/__init__.py
nonebot_plugin_firexN-0.1.7.dist-info/LICENSE
nonebot_plugin_firexN-0.1.7.dist-info/METADATA
nonebot_plugin_firexN-0.1.7.dist-info/WHEEL
nonebot_plugin_firexN-0.1.7.dist-info/top_level.txt
nonebot_plugin_firexN-0.1.7.dist-info/RECORD
