Metadata-Version: 2.1
Name: nonebot-plugin-firexN
Version: 0.1.7
Summary: nonebot plugin firexN
Home-page: https://github.com/GC-ZF/nonebot_plugin_firexN
Author: zhangshier
Author-email: 1310446718@qq.com
Keywords: pip,nonebot2,nonebot,fire,nonebot_plugin
Platform: any
Classifier: Programming Language :: Python :: 3
Classifier: License :: OSI Approved :: MIT License
Classifier: Operating System :: OS Independent
Requires-Python: >=3.7.3,<4.0
License-File: LICENSE
Requires-Dist: nonebot-plugin-apscheduler (>=0.2.0)
Requires-Dist: nonebot2 (>=2.0.0-beta.4)
Requires-Dist: nonebot-adapter-onebot (>=2.0.0-beta.1)
Requires-Dist: requests (>=2.28.1)
